swiftcl/__init__.py
swiftcl/cl.py
swiftcl/cl_kdep.py
swiftcl/coeff.py
swiftcl/interpolate.py
swiftcl-0.1.2.dist-info/METADATA
swiftcl-0.1.2.dist-info/WHEEL
swiftcl-0.1.2.dist-info/licenses/LICENSE.txt
swiftcl-0.1.2.dist-info/RECORD
