Metadata-Version: 2.4
Name: swiftcl
Version: 0.1.2
Summary: Add your description here
License-File: LICENSE.txt
Requires-Python: >=3.11
Requires-Dist: fftlog-lss
Requires-Dist: h5py>=3.10.0
Requires-Dist: interpax>=0.3.0
Requires-Dist: jax<0.5.0
Requires-Dist: mpmath>=1.3.0
Requires-Dist: numpy<2.0.0
Requires-Dist: scipy<1.13.0
